jinjang/LICENSE.txt
jinjang/README.md
jinjang/__init__.py
jinjang/__main__.py
jinjang/config/__init__.py
jinjang/config/jngflavours.py
jinjang/jngbuild.py
jinjang/jngcli.py
jinjang/jngconfig.py
jinjang/jngdata.py
jinjang-0.1.2rc0.dist-info/WHEEL
jinjang-0.1.2rc0.dist-info/entry_points.txt
jinjang-0.1.2rc0.dist-info/METADATA
jinjang-0.1.2rc0.dist-info/RECORD
