Metadata-Version: 2.1
Name: jinjang
Version: 0.1.2rc0
Summary: This project tries to ameliorate the workflow when working with the template engine Jinja
Home-page: https://github.com/bc-tools/for-dev/tree/main/jinjaNG
License: GNU License Version 3
Author: Christophe BAL
Maintainer: Christophe BAL
Requires-Python: >=3.9,<4.0
Classifier: License :: Other/Proprietary License
Classifier: Programming Language :: Python :: 3
Classifier: Programming Language :: Python :: 3.9
Classifier: Programming Language :: Python :: 3.10
Classifier: Programming Language :: Python :: 3.11
Requires-Dist: click (>=8.1,<9.0)
Requires-Dist: jinja2 (>=2.11,<3.0)
Project-URL: Repository, https://github.com/bc-tools/for-dev/tree/main/jinjaNG
